commands.py
toolbelt.py
ToolBelt_Utl-0.1.1.dist-info/LICENSE
ToolBelt_Utl-0.1.1.dist-info/METADATA
ToolBelt_Utl-0.1.1.dist-info/WHEEL
ToolBelt_Utl-0.1.1.dist-info/entry_points.txt
ToolBelt_Utl-0.1.1.dist-info/top_level.txt
ToolBelt_Utl-0.1.1.dist-info/RECORD
